mlr/__init__.py
mlr/__main__.py
mlr/core.py
mlr/exceptions.py
mlr/path.py
mlr/py.typed
multi_line_replacer-2.0.0.dist-info/WHEEL
multi_line_replacer-2.0.0.dist-info/entry_points.txt
multi_line_replacer-2.0.0.dist-info/METADATA
multi_line_replacer-2.0.0.dist-info/RECORD
