Metadata-Version: 2.4
Name: multi-line-replacer
Version: 2.0.0
Summary: A CLI utility for replacing multi-line strings in files. Supports textual replacements with wildcard matching and indentation-awareness.
Keywords: replacements,cli,command-line,utility,multi-line,multiline,string,wildcard,indentation-aware
Author: Caleb Evans
Author-email: Caleb Evans <caleb@calebevans.me>
License-Expression: MIT
Requires-Dist: rich>=14.0.0,<15.0.0
Maintainer: Caleb Evans
Maintainer-email: Caleb Evans <caleb@calebevans.me>
Requires-Python: >=3.9
Project-URL: changelog, https://github.com/caleb531/multi-line-replacer/releases
Project-URL: documentation, https://github.com/caleb531/multi-line-replacer#readme
Project-URL: homepage, https://github.com/caleb531/multi-line-replacer
Project-URL: repository, https://github.com/caleb531/multi-line-replacer
